EvoSim/__init__.py
EvoSim/controller_default.py
EvoSim/grid.py
EvoSim/interfaces.py
EvoSim/population.py
EvoSim/simulation.py
EvoSim/speciation.py
EvoSim/utils.py
EvoSim/visualizer.py
evosim-0.1.0.dist-info/licenses/LICENSE
evosim-0.1.0.dist-info/METADATA
evosim-0.1.0.dist-info/WHEEL
evosim-0.1.0.dist-info/top_level.txt
evosim-0.1.0.dist-info/RECORD
