Metadata-Version: 2.4
Name: EvoSim
Version: 0.1.0
Summary: A package for simulating evolution via the use of genetic algorithms
Author-email: Jay Nash <jnash1@conncoll.edu>
License: MIT
License-File: LICENSE
Requires-Dist: numpy>=1.23
Requires-Dist: matplotlib>=3.7
Dynamic: license-file
